{
  "unversionedId": "getting-started/intro",
  "id": "getting-started/intro",
  "isDocsHomePage": false,
  "title": "Introduction",
  "description": "What is Railflow?",
  "source": "@site/docs/getting-started/intro.md",
  "sourceDirName": "getting-started",
  "slug": "/getting-started/intro",
  "permalink": "/docs/getting-started/intro",
  "editUrl": "https://github.com/facebook/docusaurus/edit/main/website/docs/getting-started/intro.md",
  "tags": [],
  "version": "current",
  "sidebarPosition": 5,
  "frontMatter": {
    "sidebar_position": 5
  },
  "sidebar": "tutorialSidebar",
  "next": {
    "title": "Overview",
    "permalink": "/docs/railflow-cli/overview"
  }
}