{
  "unversionedId": "release-notes/cli",
  "id": "release-notes/cli",
  "isDocsHomePage": false,
  "title": "NPM CLI",
  "description": "Release: 2.1",
  "source": "@site/docs/release-notes/cli.md",
  "sourceDirName": "release-notes",
  "slug": "/release-notes/cli",
  "permalink": "/docs/release-notes/cli",
  "editUrl": "https://github.com/facebook/docusaurus/edit/main/website/docs/release-notes/cli.md",
  "tags": [],
  "version": "current",
  "sidebarPosition": 3,
  "frontMatter": {
    "sidebar_position": 3
  },
  "sidebar": "tutorialSidebar",
  "previous": {
    "title": "TeamCity Plugin",
    "permalink": "/docs/release-notes/teamcity"
  },
  "next": {
    "title": "Tutorial Introoo",
    "permalink": "/docs/intro"
  }
}